src/Dataspace.py
src/__init__.py
src/connectors.py
src/defaults.py
src/dfuncs.py
src/ffuncs.py
src/DataStream/__init__.py
src/DataStream/archive.py
src/DataStream/executors.py
src/DataStream/file.py
src/DataStream/load.py
src/DataStream/macros.py
src/DataStream/modelers.py
src/DataStream/prefect.py
src/DataStream/save.py
src/DataStream/syncs.py
src/FeatureSpace/__init__.py
src/FeatureSpace/access.py
src/FeatureSpace/add.py
src/FeatureSpace/eval.py
src/FeatureSpace/load.py
src/FeatureSpace/metadata.py
src/FeatureSpace/model.py
src/FeatureSpace/transform.py
src/FeatureSpace/view.py
dataspacetestpackage-0.0.3.dist-info/LICENSE
dataspacetestpackage-0.0.3.dist-info/METADATA
dataspacetestpackage-0.0.3.dist-info/WHEEL
dataspacetestpackage-0.0.3.dist-info/top_level.txt
dataspacetestpackage-0.0.3.dist-info/RECORD
